gaussianfilter.cpython-313-x86_64-linux-gnu.so
pygaussianfilter/LICENSE.md
pygaussianfilter/License_sacio
pygaussianfilter/__init__.py
pygaussianfilter-1.4.3.data/scripts/gf.py
pygaussianfilter-1.4.3.dist-info/licenses/LICENSE.md
pygaussianfilter-1.4.3.dist-info/METADATA
pygaussianfilter-1.4.3.dist-info/WHEEL
pygaussianfilter-1.4.3.dist-info/top_level.txt
pygaussianfilter-1.4.3.dist-info/RECORD
