Metadata-Version: 2.4
Name: pygaussianfilter
Version: 1.4.3
Summary: Python binding to gaussianfilter routine
Home-page: 
License: 3-clause BSD 2.0
Classifier: License :: OSI Approved :: BSD License
Classifier: Programming Language :: Python :: 3
Classifier: Topic :: Scientific/Engineering :: Physics
License-File: LICENSE.md
Dynamic: classifier
Dynamic: license
Dynamic: license-file
Dynamic: summary
